pypdf2htmlEX/__init__.py
pypdf2htmlEX/core.py
pypdf2htmlex-1.8.dist-info/LICENSE
pypdf2htmlex-1.8.dist-info/METADATA
pypdf2htmlex-1.8.dist-info/WHEEL
pypdf2htmlex-1.8.dist-info/top_level.txt
pypdf2htmlex-1.8.dist-info/RECORD
