Metadata-Version: 2.1
Name: pypdf2htmlex
Version: 1.8
Summary: Wrapper não oficial do pdf2htmlEX
Home-page: https://github.com/gabriel-batistuta/pypdf2htmlEX
Author: Gabriel Batistuta
Author-email: batistutag190@gmail.com
License: MIT License
Project-URL: Repository, https://github.com/gabriel-batistuta/pypdf2htmlEX
Keywords: pdf2htmlEX pdf-to-html pdf html wrapper
License-File: LICENSE
